{
    "KPlugin": {
        "Description": "A Plugin for Cantor's Panel",
        "Description[ca@valencia]": "Un connector per al quadro de Cantor",
        "Description[ca]": "Un connector per al plafó del Cantor",
        "Description[es]": "Un complemento para el panel de Cantor",
        "Description[fr]": "Un module externe pour le panneau de Cantor",
        "Description[gl]": "Un complemento para o panel de Cantor.",
        "Description[nl]": "Een plugin voor het paneel van Cantor",
        "Description[pl]": "Wtyczka dla panelu Cantor",
        "Description[sl]": "Vtičnik za Cantorjevo ploščo",
        "Description[sv]": "Ett insticksprogram för Cantors panel",
        "Description[tr]": "Cantor’un paneli için bir eklenti",
        "Description[uk]": "Додаток панелі Cantor",
        "Description[x-test]": "xxA Plugin for Cantor's Panelxx",
        "ServiceType": "Cantor/PanelPlugin"
    }
}
