{
    "KPlugin": {
        "Dependencies": [],
        "Description": "A panel to display help",
        "Description[ca@valencia]": "Un plafó per mostrar les pàgines d'ajuda",
        "Description[ca]": "Un plafó per mostrar les pàgines d'ajuda",
        "Description[cs]": "Panel pro zobrazení nápovědy",
        "Description[de]": "Eine Kontrollleiste zur Anzeige der Hilfe",
        "Description[es]": "Un panel para mostrar ayuda",
        "Description[et]": "Abi näitav paneel",
        "Description[fi]": "Paneeli ohjeiden näyttämiseen",
        "Description[fr]": "Un panneau pour afficher l'aide",
        "Description[gl]": "Un panel que mostra axuda",
        "Description[it]": "Un pannello per visualizzare aiuto",
        "Description[nl]": "Een paneel om help te tonen",
        "Description[nn]": "Eit panel som viser hjelp",
        "Description[pl]": "Panel do wyświetlania pomocy",
        "Description[pt]": "Um painel para mostrar alguma ajuda",
        "Description[pt_BR]": "Um painel para apresentar ajuda",
        "Description[ru]": "Панель для просмотра справки",
        "Description[sk]": "Panel na zobrazenie pomoci",
        "Description[sl]": "Pult za prikaz pomoči",
        "Description[sv]": "En panel för att visa hjälp",
        "Description[tr]": "Yardımı görüntülemek üzere bir panel",
        "Description[uk]": "Панель для показу довідки",
        "Description[x-test]": "xxA panel to display helpxx",
        "Description[zh_CN]": "显示帮助的面板",
        "Description[zh_TW]": "顯示說明的面板",
        "Icon": "",
        "Id": "HelpPanel",
        "License": "GPL",
        "Name": "Help",
        "Name[ca@valencia]": "Ajuda",
        "Name[ca]": "Ajuda",
        "Name[cs]": "Nápověda",
        "Name[de]": "Hilfe",
        "Name[es]": "Ayuda",
        "Name[et]": "Abi",
        "Name[fi]": "Ohjeet",
        "Name[fr]": "Aide",
        "Name[gl]": "Axuda",
        "Name[it]": "Aiuto",
        "Name[nn]": "Hjelp",
        "Name[pl]": "Pomoc",
        "Name[pt]": "Ajuda",
        "Name[pt_BR]": "Ajuda",
        "Name[ru]": "Справка",
        "Name[sk]": "Pomocník",
        "Name[sl]": "Pomoč",
        "Name[sv]": "Hjälp",
        "Name[tr]": "Yardım",
        "Name[uk]": "Довідка",
        "Name[x-test]": "xxHelpxx",
        "Name[zh_CN]": "帮助",
        "Name[zh_TW]": "求助",
        "ServiceTypes": [
            "Cantor/PanelPlugin"
        ]
    },
    "RequiredExtensions": ""
}
