<?xml version="1.0" encoding="UTF-8"?>
<sage>
  <keywords>
    <word>and</word>
    <word>del</word>
    <word>from</word>
    <word>not</word>
    <word>while</word>
    <word>as</word>
    <word>elif</word>
    <word>global</word>
    <word>or</word>
    <word>with</word>
    <word>assert</word>
    <word>else</word>
    <word>if</word>
    <word>pass</word>
    <word>yield</word>
    <word>break</word>
    <word>except</word>
    <word>import</word>
    <word>print</word>
    <word>class</word>
    <word>exec</word>
    <word>in</word>
    <word>raise</word>
    <word>continue</word>
    <word>finally</word>
    <word>is</word>
    <word>return</word>
    <word>def</word>
    <word>for</word>
    <word>lambda</word>
    <word>try</word>
  </keywords>
</sage>
