{
    "KPlugin": {
        "Dependencies": [],
        "Description": "Backend for Python Scientific Programming",
        "Description[ca@valencia]": "Dorsal per a la programació científica Python",
        "Description[ca]": "Dorsal per a la programació científica Python",
        "Description[es]": "Motor para programación científica en Python",
        "Description[et]": "Pythoni teadusliku programmeerimise taustaprogramm",
        "Description[nl]": "Backend voor wetenschappelijk programmeren in Python",
        "Description[pt]": "Infra-Estrutura de Programação Científica com Python",
        "Description[pt_BR]": "Infraestrutura de programação científica Python",
        "Description[sv]": "Bakgrundsprogram för Python vetenskaplig programmeringsmiljö",
        "Description[uk]": "Модуль наукового програмування мовою Python",
        "Description[x-test]": "xxBackend for Python Scientific Programmingxx",
        "Icon": "pythonbackend",
        "Id": "Python",
        "License": "GPL",
        "Name": "Python",
        "Name[ca@valencia]": "Python",
        "Name[ca]": "Python",
        "Name[es]": "Python",
        "Name[et]": "Python",
        "Name[nl]": "Python",
        "Name[pt]": "Python",
        "Name[pt_BR]": "Python",
        "Name[sv]": "Python",
        "Name[uk]": "Python",
        "Name[x-test]": "xxPythonxx",
        "ServiceTypes": [
            "Cantor/Backend"
        ],
        "Website": "https://python.org/"
    }
}
